notionfier/__init__.py
notionfier/api/__init__.py
notionfier/api/utils.py
notionfier/cli.py
notionfier/helpers/__init__.py
notionfier/helpers/notion_params.py
notionfier/models/__init__.py
notionfier/models/base.py
notionfier/models/block.py
notionfier/models/common.py
notionfier/models/enums.py
notionfier/modules/__init__.py
notionfier/modules/builder.py
notionfier/modules/renderer.py
notionfier-1.0.1.dist-info/LICENSE
notionfier-1.0.1.dist-info/METADATA
notionfier-1.0.1.dist-info/WHEEL
notionfier-1.0.1.dist-info/entry_points.txt
notionfier-1.0.1.dist-info/RECORD
