Metadata-Version: 2.1
Name: notionfier
Version: 1.0.1
Summary: Import markdown files to Notion
Home-page: https://github.com/Yolley/notionfier
License: MIT
Keywords: notion,markdown
Author: Yolley
Author-email: Yolley@users.noreply.github.com
Requires-Python: >=3.11,<4.0
Classifier: License :: OSI Approved :: MIT License
Classifier: Programming Language :: Python :: 3
Classifier: Programming Language :: Python :: 3.11
Classifier: Programming Language :: Python :: 3.12
Requires-Dist: click (>=8.1.7,<9.0.0)
Requires-Dist: mistune (>=3.0.2,<4.0.0)
Requires-Dist: notion-client (>=2.1.0,<3.0.0)
Project-URL: Repository, https://github.com/Yolley/notionfier
